restx_monkey/__init__.py
restx_monkey/endpoint_from_view.py
restx_monkey/restx_api.py
restx_monkey/restx_reqparser.py
restx_monkey/swagger_ui.py
restx_monkey/tools.py
restx_monkey/version_system.py
restx_monkey/werkzeug_routing.py
restx_monkey/static/droid-sans.css
restx_monkey/static/favicon-16x16.png
restx_monkey/static/favicon-32x32.png
restx_monkey/static/oauth2-redirect.html
restx_monkey/static/swagger-ui-bundle.js
restx_monkey/static/swagger-ui-bundle.js.map
restx_monkey/static/swagger-ui-es-bundle-core.js
restx_monkey/static/swagger-ui-es-bundle-core.js.map
restx_monkey/static/swagger-ui-es-bundle.js
restx_monkey/static/swagger-ui-es-bundle.js.map
restx_monkey/static/swagger-ui-standalone-preset.js
restx_monkey/static/swagger-ui-standalone-preset.js.map
restx_monkey/static/swagger-ui.css
restx_monkey/static/swagger-ui.css.map
restx_monkey/static/swagger-ui.js
restx_monkey/static/swagger-ui.js.map
restx_monkey-0.6.1.dist-info/LICENSE
restx_monkey-0.6.1.dist-info/METADATA
restx_monkey-0.6.1.dist-info/WHEEL
restx_monkey-0.6.1.dist-info/top_level.txt
restx_monkey-0.6.1.dist-info/RECORD
