Metadata-Version: 2.1
Name: restx-monkey
Version: 0.6.1
Summary: Monkey patches to keep flask-restx working with latest flask and werkzeug.
Author-email: Tom Trval <thandeus@gmail.com>
License: BSD-3-Clause
Project-URL: Homepage, https://github.com/Ryu-CZ/restx-monkey
Project-URL: Bug Tracker, https://github.com/Ryu-CZ/restx-monkey/issues
Keywords: restx,flask-restx,api,rest,flask,restplus,json,openapi,python
Classifier: License :: OSI Approved :: BSD License
Classifier: Operating System :: OS Independent
Classifier: Development Status :: 5 - Production/Stable
Classifier: Intended Audience :: Developers
Classifier: Topic :: Internet :: WWW/HTTP :: WSGI :: Server
Classifier: Framework :: Flask
Classifier: Programming Language :: Python :: 3
Classifier: Typing :: Typed
Requires-Python: >=3.8
License-File: LICENSE
Requires-Dist: flask-restx >=0.1
